AutoDocker/__init__.py
AutoDocker/main.py
AutoDocker-0.3.0.dist-info/LICENSE
AutoDocker-0.3.0.dist-info/METADATA
AutoDocker-0.3.0.dist-info/WHEEL
AutoDocker-0.3.0.dist-info/top_level.txt
AutoDocker-0.3.0.dist-info/RECORD
