Metadata-Version: 2.1
Name: AutoDocker
Version: 0.3.0
Summary: Simple program to quickly dock ligands using Autodock Vina
Home-page: https://github.com/aakognole/autodocker
Author: Abhishek Kognole
Author-email: aakognole@gmail.com
Project-URL: Bug Tracker, https://github.com/aakognole/autodocker/issues
Classifier: Programming Language :: Python :: 3
Classifier: License :: OSI Approved :: MIT License
Classifier: Operating System :: OS Independent
Requires-Python: >=3.9
License-File: LICENSE
Requires-Dist: ligprepper >=0.5
